spatialclock/__init__.py
spatialclock/deploy.py
spatialclock/develop.py
spatialclock/proximity.py
spatialclock/utils.py
spatialclock/clocks/lasso_cv5_nalphas20_spatialsmooth_alpha08_neigh20_Astrocyte.pkl
spatialclock/clocks/lasso_cv5_nalphas20_spatialsmooth_alpha08_neigh20_B cell.pkl
spatialclock/clocks/lasso_cv5_nalphas20_spatialsmooth_alpha08_neigh20_Endothelial.pkl
spatialclock/clocks/lasso_cv5_nalphas20_spatialsmooth_alpha08_neigh20_Ependymal.pkl
spatialclock/clocks/lasso_cv5_nalphas20_spatialsmooth_alpha08_neigh20_Macrophage.pkl
spatialclock/clocks/lasso_cv5_nalphas20_spatialsmooth_alpha08_neigh20_Microglia.pkl
spatialclock/clocks/lasso_cv5_nalphas20_spatialsmooth_alpha08_neigh20_NSC.pkl
spatialclock/clocks/lasso_cv5_nalphas20_spatialsmooth_alpha08_neigh20_Neuroblast.pkl
spatialclock/clocks/lasso_cv5_nalphas20_spatialsmooth_alpha08_neigh20_Neuron-Excitatory.pkl
spatialclock/clocks/lasso_cv5_nalphas20_spatialsmooth_alpha08_neigh20_Neuron-Inhibitory.pkl
spatialclock/clocks/lasso_cv5_nalphas20_spatialsmooth_alpha08_neigh20_Neuron-MSN.pkl
spatialclock/clocks/lasso_cv5_nalphas20_spatialsmooth_alpha08_neigh20_Neutrophil.pkl
spatialclock/clocks/lasso_cv5_nalphas20_spatialsmooth_alpha08_neigh20_OPC.pkl
spatialclock/clocks/lasso_cv5_nalphas20_spatialsmooth_alpha08_neigh20_Oligodendrocyte.pkl
spatialclock/clocks/lasso_cv5_nalphas20_spatialsmooth_alpha08_neigh20_Pericyte.pkl
spatialclock/clocks/lasso_cv5_nalphas20_spatialsmooth_alpha08_neigh20_T cell.pkl
spatialclock/clocks/lasso_cv5_nalphas20_spatialsmooth_alpha08_neigh20_VLMC.pkl
spatialclock/clocks/lasso_cv5_nalphas20_spatialsmooth_alpha08_neigh20_VSMC.pkl
spatialclock/clocks/mean_impute_files/lasso_cv5_nalphas20_spatialsmooth_alpha08_neigh20_Astrocyte.csv
spatialclock/clocks/mean_impute_files/lasso_cv5_nalphas20_spatialsmooth_alpha08_neigh20_B cell.csv
spatialclock/clocks/mean_impute_files/lasso_cv5_nalphas20_spatialsmooth_alpha08_neigh20_Endothelial.csv
spatial_aging_clock-0.0.2.dist-info/LICENSE
spatial_aging_clock-0.0.2.dist-info/WHEEL
spatial_aging_clock-0.0.2.dist-info/METADATA
spatial_aging_clock-0.0.2.dist-info/RECORD
