Metadata-Version: 2.1
Name: spatial-aging-clock
Version: 0.0.2
Summary: Spatial Aging Clock
Author-email: Eric Sun <edsun97@gmail.com>
Classifier: License :: OSI Approved :: MIT License
Requires-Dist: squidpy>=1.1.2
Requires-Dist: anndata>=0.8.0
Requires-Dist: scanpy>=1.9.1
Project-URL: Home, https://github.com/sunericd/SpatialAgingClock
